pyprestascan/__init__.py
pyprestascan/__main__.py
pyprestascan/cli.py
pyprestascan/ai/__init__.py
pyprestascan/ai/providers.py
pyprestascan/assets/bootstrap.min.css
pyprestascan/assets/chart.min.js
pyprestascan/assets/datatables.min.css
pyprestascan/assets/datatables.min.js
pyprestascan/assets/report.css
pyprestascan/core/__init__.py
pyprestascan/core/analyzer.py
pyprestascan/core/cache.py
pyprestascan/core/config_validation.py
pyprestascan/core/crawler.py
pyprestascan/core/db_pool.py
pyprestascan/core/exporters.py
pyprestascan/core/fetcher.py
pyprestascan/core/fixer.py
pyprestascan/core/parser.py
pyprestascan/core/performance.py
pyprestascan/core/security.py
pyprestascan/core/storage.py
pyprestascan/core/utils.py
pyprestascan/gui/__init__.py
pyprestascan/gui/__main__.py
pyprestascan/gui/app.py
pyprestascan/gui/i18n.py
pyprestascan/gui/main_window.py
pyprestascan/gui/scan_profiles.py
pyprestascan/gui/themes.py
pyprestascan/integrations/__init__.py
pyprestascan/integrations/excel_exporter.py
pyprestascan/integrations/prestashop_api.py
pyprestascan/integrations/webhook_client.py
pyprestascan/reports/templates/report.html.j2
pyprestascan-1.7.3.dist-info/licenses/LICENSE
pyprestascan-1.7.3.dist-info/METADATA
pyprestascan-1.7.3.dist-info/WHEEL
pyprestascan-1.7.3.dist-info/entry_points.txt
pyprestascan-1.7.3.dist-info/top_level.txt
pyprestascan-1.7.3.dist-info/RECORD
