Metadata-Version: 2.4
Name: pyprestascan
Version: 1.7.3
Summary: Scanner SEO professionale per PrestaShop con fix AI-powered (DeepSeek/GPT/Claude), export Excel e API integration - GUI e CLI
Author-email: Andrea Piani <info@andreapiani.com>
License: MIT
Project-URL: Homepage, https://github.com/andreapianidev/pyprestascan
Project-URL: Repository, https://github.com/andreapianidev/pyprestascan
Project-URL: Issues, https://github.com/andreapianidev/pyprestascan/issues
Project-URL: Documentation, https://github.com/andreapianidev/pyprestascan#readme
Project-URL: Author, https://linktr.ee/andreapianidev
Keywords: seo,prestashop,ecommerce,crawler,analysis
Classifier: Development Status :: 4 - Beta
Classifier: Intended Audience :: Developers
Classifier: License :: OSI Approved :: MIT License
Classifier: Programming Language :: Python :: 3
Classifier: Programming Language :: Python :: 3.11
Classifier: Programming Language :: Python :: 3.12
Classifier: Topic :: Internet :: WWW/HTTP
Classifier: Topic :: Software Development :: Libraries :: Python Modules
Requires-Python: >=3.8
License-File: LICENSE
Requires-Dist: httpx[brotli]>=0.25.0
Requires-Dist: aiolimiter>=1.1.0
Requires-Dist: selectolax>=0.3.17
Requires-Dist: lxml>=4.9.3
Requires-Dist: urllib3>=2.0.0
Requires-Dist: protego>=0.3.0
Requires-Dist: jinja2>=3.1.2
Requires-Dist: rich>=13.7.0
Requires-Dist: pydantic>=2.5.0
Requires-Dist: pandas>=2.1.0
Requires-Dist: aiosqlite>=0.19.0
Requires-Dist: click>=8.1.7
Requires-Dist: xlsxwriter>=3.0.0
Provides-Extra: dev
Requires-Dist: pytest>=7.4.0; extra == "dev"
Requires-Dist: pytest-asyncio>=0.21.1; extra == "dev"
Requires-Dist: pytest-cov>=4.1.0; extra == "dev"
Requires-Dist: black>=23.9.0; extra == "dev"
Requires-Dist: flake8>=6.1.0; extra == "dev"
Requires-Dist: mypy>=1.6.0; extra == "dev"
Requires-Dist: pyinstaller>=6.0.0; extra == "dev"
Provides-Extra: gui
Requires-Dist: PySide6>=6.6.0; extra == "gui"
Dynamic: license-file
